AUTHORS
CHANGELOG.txt
DESCRIPTION
LICENSE
MANIFEST.in
README.rst
setup.py
django_multilingual_news.egg-info/PKG-INFO
django_multilingual_news.egg-info/SOURCES.txt
django_multilingual_news.egg-info/dependency_links.txt
django_multilingual_news.egg-info/requires.txt
django_multilingual_news.egg-info/top_level.txt
multilingual_news/__init__.py
multilingual_news/admin.py
multilingual_news/app_settings.py
multilingual_news/cms_apps.py
multilingual_news/cms_plugins.py
multilingual_news/feeds.py
multilingual_news/models.py
multilingual_news/sitemaps.py
multilingual_news/urls.py
multilingual_news/views.py
multilingual_news/locale/de/LC_MESSAGES/django.mo
multilingual_news/locale/de/LC_MESSAGES/django.po
multilingual_news/locale/fa/LC_MESSAGES/django.mo
multilingual_news/locale/fa/LC_MESSAGES/django.po
multilingual_news/migrations/0001_initial.py
multilingual_news/migrations/0002_recentplugin.py
multilingual_news/migrations/__init__.py
multilingual_news/south_migrations/0001_initial.py
multilingual_news/south_migrations/0002_auto__add_recentplugin.py
multilingual_news/south_migrations/0003_auto__add_field_newsentry_image_float.py
multilingual_news/south_migrations/0004_auto__add_field_newsentry_image_width__add_field_newsentry_image_heigh.py
multilingual_news/south_migrations/0005_auto__add_field_newsentry_excerpt__add_field_newsentry_content.py
multilingual_news/south_migrations/0006_migrate_placeholder_fields.py
multilingual_news/south_migrations/0007_auto.py
multilingual_news/south_migrations/0008_auto__add_newsentrytranslation__add_unique_newsentrytranslation_langua.py
multilingual_news/south_migrations/0009_migrate_i18n_fields.py
multilingual_news/south_migrations/0010_auto__del_newsentrytitle.py
multilingual_news/south_migrations/0011_auto__add_category__add_categoryplugin__add_categorytranslation__add_u.py
multilingual_news/south_migrations/0012_correct_slot_name.py
multilingual_news/south_migrations/0013_auto__add_field_newsentrytranslation_meta_title__add_field_newsentrytr.py
multilingual_news/south_migrations/0014_auto__add_field_newsentry_author_user.py
multilingual_news/south_migrations/0015_auto__chg_field_newsentry_author.py
