Metadata-Version: 1.0
Name: django-multilingual-news
Version: 2.6.9
Summary: A reusable Django app for managing news/blog entries in different languages.
